[
    {
        "id": "about-page-header-data",
        "title": "About South Island Fireplace & Spas",
        "desc": "We are Vancouver Island's largest retailer of fireplaces and stoves",
        "bg_image": "../images/banner/showroom_stove.jpg"
    },
    {
        "id": "about-page-intro",
        "section_title": {
            "title": "Visit our store as we are regularly upgrading our modern showroom",
            "subtitle": "our company"
        },
        "heading": "<mark>25+</mark> YEARS EXPERIENCE",
        "text": "",
        "desc": "We provide installation and on-going service for all our customers. Our large and dedicated sales and service staff are trained in all the products we sell, ensuring you get the appliance best suited for you and your home.",
        "path": "leadership"
    }
]